eagle/__init__.py
eagle/const.py
eagle/localapi.py
rfa_eagle_api-0.0.6.dist-info/LICENSE
rfa_eagle_api-0.0.6.dist-info/METADATA
rfa_eagle_api-0.0.6.dist-info/WHEEL
rfa_eagle_api-0.0.6.dist-info/top_level.txt
rfa_eagle_api-0.0.6.dist-info/RECORD
