Metadata-Version: 2.1
Name: rfa-eagle-api
Version: 0.0.6
Summary: Unofficial client SDK for Rainforest Automation Eagle-200
Home-page: https://github.com/tonymitchell/rfa-eagle-api
Author: Tony Mitchell
Author-email: tony.mitchell@live.ca
License: MIT
Platform: UNKNOWN
Classifier: Programming Language :: Python :: 3
Classifier: License :: OSI Approved :: MIT License
Classifier: Operating System :: OS Independent
Requires-Dist: lxml
Requires-Dist: requests
Requires-Dist: inflection
